factorion/__init__.py
factorion/api/__init__.py
factorion/api/base.py
factorion/api/decorators.py
factorion/billing/__init__.py
factorion-0.0.0.data/scripts/factorion
factorion-0.0.0.dist-info/LICENSE
factorion-0.0.0.dist-info/METADATA
factorion-0.0.0.dist-info/WHEEL
factorion-0.0.0.dist-info/top_level.txt
factorion-0.0.0.dist-info/RECORD
