Metadata-Version: 2.1
Name: factorion
Version: 0.0.0
Summary: A Collection of Prediction APIs
Home-page: https://www.factorion.ai
Author: Dr. Yves-Laurent Kom Samo
Author-email: github@factorion.ai
License: GPLv3
Download-URL: https://github.com/kxytechnologies/factorion/archive/v0.0.0.tar.gz
Project-URL: Documentation, https://www.factorion.ai/reference
Project-URL: Source Code, https://github.com/kxytechnologies/factorion/
Keywords: Prediction API
Platform: UNKNOWN
Classifier: Environment :: Console
Classifier: Intended Audience :: Developers
Classifier: Intended Audience :: Education
Classifier: Intended Audience :: Science/Research
Classifier: Intended Audience :: Information Technology
Classifier: Natural Language :: English
Classifier: Operating System :: OS Independent
Classifier: Topic :: Scientific/Engineering :: Artificial Intelligence
Classifier: Topic :: Scientific/Engineering :: Information Analysis
Classifier: License :: OSI Approved :: GNU General Public License v3 or later (GPLv3+)
Classifier: Programming Language :: Python :: 3 :: Only
Classifier: Development Status :: 5 - Production/Stable
Classifier: Topic :: Scientific/Engineering :: Artificial Intelligence
Classifier: Topic :: Scientific/Engineering :: Mathematics
License-File: LICENSE
Requires-Dist: numpy (>=1.13.1)
Requires-Dist: scipy (>=1.4.1)
Requires-Dist: pandas (>=0.23.0)
Requires-Dist: requests (>=2.22.0)
